pixian_ai/__init__.py
pixian_ai/client.py
pixian_ai/utils.py
pixian_ai-1.0.0.dist-info/METADATA
pixian_ai-1.0.0.dist-info/WHEEL
pixian_ai-1.0.0.dist-info/top_level.txt
pixian_ai-1.0.0.dist-info/RECORD
