Metadata-Version: 2.1
Name: pixian-ai
Version: 1.0.0
Summary: Python SDK for pixian.ai
Home-page: https://github.com/mitchbregs/pixian-ai
Author: Mitchell Bregman
Author-email: mitch@mitchbregs.com
Keywords: pixian.ai remove background
Classifier: Development Status :: 3 - Alpha
Classifier: Intended Audience :: Developers
Classifier: Programming Language :: Python :: 3
Requires-Python: >3.6
Requires-Dist: requests
